s2rcp/__init__.py
s2rcp/core/__init__.py
s2rcp/core/container.py
s2rcp/core/exceptions.py
s2rcp/core/utils.py
s2rcp/core/commands/__init__.py
s2rcp/core/commands/all_commands.py
s2rcp/core/commands/command.py
s2rcp/core/commands/start_command.py
s2rcp/core/commands/stop_command.py
s2rcp/network/__init__.py
s2rcp/network/client.py
s2rcp/network/tcp_client.py
s2rcp/remote/__init__.py
s2rcp/remote/axes.py
s2rcp/remote/encoder.py
s2rcp/remote/remote_controller.py
s2rcp/remote/robot_model.py
s2rcp/robot/__init__.py
s2rcp/robot/decoder.py
s2rcp/robot/motor.py
s2rcp/robot/motors_controller.py
s2rcp-1.0.0.dist-info/LICENSE.txt
s2rcp-1.0.0.dist-info/METADATA
s2rcp-1.0.0.dist-info/WHEEL
s2rcp-1.0.0.dist-info/top_level.txt
s2rcp-1.0.0.dist-info/RECORD
