Metadata-Version: 2.1
Name: s2rcp
Version: 1.0.0
Summary: Simple Remote Robot Control Protocol
Home-page: https://gitlab.com/zhikh/s2rcp
Author: zhikh
Author-email: zhikh.k@gmail.com
Classifier: Programming Language :: Python :: 3
Classifier: License :: OSI Approved :: MIT License
Classifier: Operating System :: OS Independent
Requires-Python: >=3.5
License-File: LICENSE.txt
